{
  "_class": "artboard",
  "backgroundColor": {
    "_class": "color",
    "alpha": 1,
    "blue": 0.996078431372549,
    "do_objectID": "C7E01C77-69B6-4724-A935-B34F93AEFBE6",
    "green": 0.9921568627450981,
    "red": 0.9882352941176471
  },
  "do_objectID": "0B547501-1618-4FD9-9C86-EDC4FE6D2205",
  "exportOptions": {
    "_class": "exportOptions",
    "exportFormats": [
    ],
    "includedLayerIds": [
    ],
    "layerOptions": 0,
    "shouldTrim": false
  },
  "frame": {
    "_class": "rect",
    "constrainProportions": false,
    "do_objectID": "825B824F-9A8E-469E-9F08-5416D381FB1A",
    "height": 1376,
    "width": 1440,
    "x": 5626,
    "y": 1056
  },
  "hasBackgroundColor": false,
  "hasClickThrough": true,
  "horizontalRulerData": {
    "_class": "rulerData",
    "base": 0,
    "do_objectID": "FDCCCB7B-B8D3-43D3-B5BE-4397C1AE0A5C",
    "guides": [
    ]
  },
  "includeBackgroundColorInExport": true,
  "includeInCloudUpload": true,
  "isFlippedHorizontal": false,
  "isFlippedVertical": false,
  "isFlowHome": false,
  "isLocked": false,
  "isVisible": true,
  "layerListExpandedType": 2,
  "layers": [
    {
      "class": "group",
      "id": "DFA750BD-8A44-4213-A320-C5568EB30736"
    },
    {
      "class": "symbolInstance",
      "id": "F6E51FB6-7056-4E19-84CD-E73293E3FC28"
    },
    {
      "class": "symbolInstance",
      "id": "6EE9B392-1C30-49D6-87A8-6F099AC0CB09"
    }
  ],
  "layout": {
    "_class": "layoutGrid",
    "columnWidth": 65,
    "do_objectID": "F30ECFC3-0F99-48F0-AE05-1E83B5D9CAB9",
    "drawHorizontal": false,
    "drawHorizontalLines": false,
    "drawVertical": true,
    "gutterHeight": 12,
    "gutterWidth": 30,
    "guttersOutside": true,
    "horizontalOffset": 150,
    "isEnabled": false,
    "numberOfColumns": 12,
    "rowHeightMultiplication": 5,
    "totalWidth": 1140
  },
  "name": "Profile / Individual / Owner / Blank / Followed",
  "nameIsFixed": false,
  "presetDictionary": {
    "allowResizedMatching": 0,
    "height": 1024,
    "name": "Desktop HD",
    "offersLandscapeVariant": 0,
    "width": 1440
  },
  "resizesContent": false,
  "resizingConstraint": 63,
  "resizingType": 0,
  "rotation": 0,
  "shouldBreakMaskChain": true,
  "style": {
    "_class": "style",
    "endDecorationType": 0,
    "miterLimit": 10,
    "startDecorationType": 0
  },
  "userInfo": {
    "com.animaapp.stc-sketch-plugin": {
      "kModelPropertiesKey": {
      }
    }
  },
  "verticalRulerData": {
    "_class": "rulerData",
    "base": 0,
    "do_objectID": "8CE26FBB-2F95-4B72-BE51-D5E0682EFE8A",
    "guides": [
    ]
  }
}