{
  "_class": "group",
  "do_objectID": "30EC87D5-B6C1-4600-92A0-EC9C6CC2421B",
  "exportOptions": {
    "_class": "exportOptions",
    "do_objectID": "10F94DB8-6BB5-405B-91E6-0C7139FF0DF5",
    "exportFormats": [
      {
        "_class": "exportFormat",
        "absoluteSize": 0,
        "fileFormat": "png",
        "name": "",
        "namingScheme": 0,
        "scale": 1,
        "visibleScaleType": 0
      },
      {
        "_class": "exportFormat",
        "absoluteSize": 0,
        "fileFormat": "png",
        "name": "@2x",
        "namingScheme": 0,
        "scale": 2,
        "visibleScaleType": 0
      },
      {
        "_class": "exportFormat",
        "absoluteSize": 0,
        "fileFormat": "png",
        "name": "@3x",
        "namingScheme": 0,
        "scale": 3,
        "visibleScaleType": 0
      }
    ],
    "includedLayerIds": [
    ],
    "layerOptions": 0,
    "shouldTrim": false
  },
  "frame": {
    "_class": "rect",
    "constrainProportions": false,
    "do_objectID": "B686EDAA-B915-40B3-8F9C-2CCA0ACA6B2C",
    "height": 120,
    "width": 331,
    "x": 22,
    "y": 76
  },
  "hasClickThrough": false,
  "isFlippedHorizontal": false,
  "isFlippedVertical": false,
  "isLocked": false,
  "isVisible": true,
  "layerListExpandedType": 2,
  "layers": [
    {
      "class": "shapeGroup",
      "id": "B7942098-23FF-4169-BADC-70EBFACEB5DD"
    },
    {
      "class": "shapeGroup",
      "id": "BEA53A86-E881-42D2-8450-03E657E6D8C7"
    }
  ],
  "name": "Shipping",
  "nameIsFixed": true,
  "resizingConstraint": 63,
  "resizingType": 0,
  "rotation": 0,
  "shouldBreakMaskChain": false,
  "style": {
    "_class": "style",
    "do_objectID": "6E248F17-19F3-452B-8612-5FFC30FBDB99",
    "endDecorationType": 0,
    "miterLimit": 10,
    "startDecorationType": 0
  },
  "userInfo": {
    "com.animaapp.stc-sketch-plugin": {
      "kModelPropertiesKey": {
      }
    }
  }
}