{
  "_class": "shapeGroup",
  "clippingMaskMode": 0,
  "do_objectID": "DEFFA036-6992-4F1A-A88D-9EF5678B399C",
  "exportOptions": {
    "_class": "exportOptions",
    "do_objectID": "1CEE5F37-4DA4-4EC4-BFD0-19ABA20442FC",
    "exportFormats": [
    ],
    "includedLayerIds": [
    ],
    "layerOptions": 0,
    "shouldTrim": false
  },
  "frame": {
    "_class": "rect",
    "constrainProportions": false,
    "do_objectID": "7D0C296C-F199-4117-B0FA-4DFC1CC7FE04",
    "height": 40.1,
    "width": 54.63638392857145,
    "x": 0,
    "y": 0.044444444444447
  },
  "hasClickThrough": false,
  "hasClippingMask": false,
  "isFlippedHorizontal": false,
  "isFlippedVertical": false,
  "isLocked": false,
  "isVisible": true,
  "layerListExpandedType": 0,
  "layers": [
    {
      "class": "shapePath",
      "id": "41C6BC12-D34C-4053-A29B-3F06C5688F1B"
    }
  ],
  "name": "Shape",
  "nameIsFixed": false,
  "resizingConstraint": 63,
  "resizingType": 0,
  "rotation": 0,
  "shouldBreakMaskChain": false,
  "style": {
    "_class": "style",
    "do_objectID": "9AAF81B9-0247-4858-808A-C08085D105F7",
    "endDecorationType": 0,
    "fills": [
      {
        "_class": "fill",
        "color": {
          "_class": "color",
          "alpha": 0.6,
          "blue": 0.6470588235294118,
          "green": 0.5843137254901961,
          "red": 0.5490196078431373
        },
        "fillType": 0,
        "isEnabled": true,
        "noiseIndex": 0,
        "noiseIntensity": 0,
        "patternFillType": 1,
        "patternTileScale": 1
      }
    ],
    "miterLimit": 10,
    "startDecorationType": 0
  },
  "userInfo": {
    "com.animaapp.stc-sketch-plugin": {
      "kModelPropertiesKey": {
      }
    }
  },
  "windingRule": 0
}