{
  "_class": "shapeGroup",
  "clippingMaskMode": 0,
  "do_objectID": "6D43E2BC-1F7A-44DC-8B42-0F69E845F545",
  "exportOptions": {
    "_class": "exportOptions",
    "do_objectID": "52E306B8-698F-4958-8221-AC32C5F62F09",
    "exportFormats": [
    ],
    "includedLayerIds": [
    ],
    "layerOptions": 0,
    "shouldTrim": false
  },
  "frame": {
    "_class": "rect",
    "constrainProportions": false,
    "do_objectID": "A7B6EBF9-4ADE-43DF-B21D-C2DED21D3628",
    "height": 2.617647058823532,
    "width": 2.588235294117642,
    "x": 0,
    "y": 0.0147058823529403
  },
  "hasClickThrough": false,
  "hasClippingMask": false,
  "isFlippedHorizontal": false,
  "isFlippedVertical": false,
  "isLocked": false,
  "isVisible": true,
  "layerListExpandedType": 0,
  "layers": [
    {
      "class": "shapePath",
      "id": "271E9615-DAC6-43F1-B4D4-DA92346EF9B0"
    }
  ],
  "name": "Shape",
  "nameIsFixed": false,
  "resizingConstraint": 63,
  "resizingType": 0,
  "rotation": 0,
  "shouldBreakMaskChain": false,
  "style": {
    "_class": "style",
    "do_objectID": "2DCFA15E-4366-43F6-A746-8AD42FD81791",
    "endDecorationType": 0,
    "fills": [
      {
        "_class": "fill",
        "color": {
          "_class": "color",
          "alpha": 1,
          "blue": 0.7176470588235294,
          "green": 0.6980392156862744,
          "red": 0.1137254901960785
        },
        "fillType": 0,
        "isEnabled": true,
        "noiseIndex": 0,
        "noiseIntensity": 0,
        "patternFillType": 1,
        "patternTileScale": 1
      }
    ],
    "miterLimit": 10,
    "startDecorationType": 0
  },
  "userInfo": {
    "com.animaapp.stc-sketch-plugin": {
      "kModelPropertiesKey": {
      }
    }
  },
  "windingRule": 0
}