{
  "_class": "group",
  "do_objectID": "FD4FA711-F7DF-4776-87A7-45F7144C5380",
  "exportOptions": {
    "_class": "exportOptions",
    "exportFormats": [
    ],
    "includedLayerIds": [
    ],
    "layerOptions": 0,
    "shouldTrim": false
  },
  "frame": {
    "_class": "rect",
    "constrainProportions": false,
    "do_objectID": "79429F82-B08C-4972-84BF-36B3BE85C5A6",
    "height": 33,
    "width": 46,
    "x": 135,
    "y": 0
  },
  "hasClickThrough": false,
  "isFlippedHorizontal": false,
  "isFlippedVertical": false,
  "isLocked": false,
  "isVisible": true,
  "layerListExpandedType": 0,
  "layers": [
    {
      "class": "shapeGroup",
      "id": "6201B9F2-1ED8-4926-8D59-DEA16AC18CFB"
    },
    {
      "class": "text",
      "id": "337F04A7-D548-459D-A383-F052F4E469F5"
    }
  ],
  "name": "Contents / Profile / Individual / Tab Number",
  "nameIsFixed": false,
  "resizingConstraint": 63,
  "resizingType": 0,
  "rotation": 0,
  "shouldBreakMaskChain": false,
  "style": {
    "_class": "style",
    "do_objectID": "697DA396-D76B-4FE9-B3A9-93437C674A53",
    "endDecorationType": 0,
    "miterLimit": 10,
    "startDecorationType": 0
  },
  "userInfo": {
    "com.animaapp.stc-sketch-plugin": {
      "kModelPropertiesKey": {
      }
    }
  }
}