{
  "_class": "shapePath",
  "booleanOperation": -1,
  "do_objectID": "3C9D1DA5-F266-4871-B562-FCBB3B44EC34",
  "edited": true,
  "exportOptions": {
    "_class": "exportOptions",
    "exportFormats": [
    ],
    "includedLayerIds": [
    ],
    "layerOptions": 0,
    "shouldTrim": false
  },
  "frame": {
    "_class": "rect",
    "constrainProportions": false,
    "do_objectID": "64B723FE-E711-4EB3-9714-47876039729D",
    "height": 1.638429308981889,
    "width": 8.226103394465316,
    "x": 0,
    "y": 0
  },
  "isClosed": true,
  "isFlippedHorizontal": false,
  "isFlippedVertical": false,
  "isLocked": false,
  "isVisible": true,
  "layerListExpandedType": 0,
  "name": "Path",
  "nameIsFixed": false,
  "pointRadiusBehaviour": 1,
  "points": [
    {
      "_class": "curvePoint",
      "cornerRadius": 0,
      "curveFrom": "{0.89999718750878921, 1}",
      "curveMode": 4,
      "curveTo": "{0.9552251399214382, 1}",
      "hasCurveFrom": false,
      "hasCurveTo": true,
      "point": "{0.89999718750878921, 1}"
    },
    {
      "_class": "curvePoint",
      "cornerRadius": 0,
      "curveFrom": "{0.04477486007856183, 1}",
      "curveMode": 4,
      "curveTo": "{0.10000281249121074, 1}",
      "hasCurveFrom": true,
      "hasCurveTo": false,
      "point": "{0.10000281249121074, 1}"
    },
    {
      "_class": "curvePoint",
      "cornerRadius": 0,
      "curveFrom": "{0, 0.22386800412487157}",
      "curveMode": 2,
      "curveTo": "{0, 0.77613199587512849}",
      "hasCurveFrom": true,
      "hasCurveTo": true,
      "point": "{0, 0.5}"
    },
    {
      "_class": "curvePoint",
      "cornerRadius": 0,
      "curveFrom": "{0.10000281249121074, 0}",
      "curveMode": 4,
      "curveTo": "{0.044774860078562365, 0}",
      "hasCurveFrom": false,
      "hasCurveTo": true,
      "point": "{0.10000281249121074, 0}"
    },
    {
      "_class": "curvePoint",
      "cornerRadius": 0,
      "curveFrom": "{0.9552251399214382, 0}",
      "curveMode": 4,
      "curveTo": "{0.89999718750878921, 0}",
      "hasCurveFrom": true,
      "hasCurveTo": false,
      "point": "{0.89999718750878921, 0}"
    },
    {
      "_class": "curvePoint",
      "cornerRadius": 0,
      "curveFrom": "{1, 0.77613199587512849}",
      "curveMode": 2,
      "curveTo": "{1, 0.22386800412487157}",
      "hasCurveFrom": true,
      "hasCurveTo": true,
      "point": "{1, 0.5}"
    }
  ],
  "resizingConstraint": 63,
  "resizingType": 0,
  "rotation": 0,
  "shouldBreakMaskChain": false,
  "userInfo": {
    "com.animaapp.stc-sketch-plugin": {
      "kModelPropertiesKey": {
      }
    }
  }
}