{
  "_class": "shapePath",
  "booleanOperation": -1,
  "do_objectID": "18365955-E719-487D-A58C-BE94B19DD4FC",
  "edited": true,
  "exportOptions": {
    "_class": "exportOptions",
    "exportFormats": [
    ],
    "includedLayerIds": [
    ],
    "layerOptions": 0,
    "shouldTrim": false
  },
  "frame": {
    "_class": "rect",
    "constrainProportions": false,
    "height": 5.714285714285714,
    "width": 1,
    "x": 0,
    "y": 13.75661371428571
  },
  "isClosed": true,
  "isFlippedHorizontal": false,
  "isFlippedVertical": false,
  "isLocked": false,
  "isVisible": true,
  "layerListExpandedType": 0,
  "name": "Shape-path",
  "nameIsFixed": false,
  "pointRadiusBehaviour": 1,
  "points": [
    {
      "_class": "curvePoint",
      "cornerRadius": 0,
      "curveFrom": "{1, 0.96269040000000017}",
      "curveMode": 4,
      "curveTo": "{1, 0.91666666666666663}",
      "hasCurveFrom": true,
      "hasCurveTo": false,
      "point": "{1, 0.91666666666666663}"
    },
    {
      "_class": "curvePoint",
      "cornerRadius": 0,
      "curveFrom": "{0.22385762499999995, 1}",
      "curveMode": 2,
      "curveTo": "{0.77614237000000008, 1}",
      "hasCurveFrom": true,
      "hasCurveTo": true,
      "point": "{0.5, 1}"
    },
    {
      "_class": "curvePoint",
      "cornerRadius": 0,
      "curveFrom": "{0, 0.91666666666666663}",
      "curveMode": 4,
      "curveTo": "{0, 0.96269040000000017}",
      "hasCurveFrom": false,
      "hasCurveTo": true,
      "point": "{0, 0.91666666666666663}"
    },
    {
      "_class": "curvePoint",
      "cornerRadius": 0,
      "curveFrom": "{0, 0.03730961666666667}",
      "curveMode": 4,
      "curveTo": "{0, 0.083333333333333356}",
      "hasCurveFrom": true,
      "hasCurveTo": false,
      "point": "{0, 0.083333333333333356}"
    },
    {
      "_class": "curvePoint",
      "cornerRadius": 0,
      "curveFrom": "{0.77614237000000008, 0}",
      "curveMode": 2,
      "curveTo": "{0.22385762499999995, 0}",
      "hasCurveFrom": true,
      "hasCurveTo": true,
      "point": "{0.5, 0}"
    },
    {
      "_class": "curvePoint",
      "cornerRadius": 0,
      "curveFrom": "{1, 0.083333333333333356}",
      "curveMode": 4,
      "curveTo": "{1, 0.03730961666666667}",
      "hasCurveFrom": false,
      "hasCurveTo": true,
      "point": "{1, 0.083333333333333356}"
    }
  ],
  "resizingConstraint": 63,
  "resizingType": 0,
  "rotation": 0,
  "shouldBreakMaskChain": false
}