{
  "_class": "group",
  "do_objectID": "4AC0EB8A-6E20-4306-BD39-CD207F0BDE8D",
  "exportOptions": {
    "_class": "exportOptions",
    "exportFormats": [
    ],
    "includedLayerIds": [
    ],
    "layerOptions": 0,
    "shouldTrim": false
  },
  "frame": {
    "_class": "rect",
    "constrainProportions": false,
    "height": 16,
    "width": 132,
    "x": 395,
    "y": 390
  },
  "hasClickThrough": false,
  "isFlippedHorizontal": false,
  "isFlippedVertical": false,
  "isLocked": false,
  "isVisible": true,
  "layerListExpandedType": 0,
  "layers": [
    {
      "class": "text",
      "id": "1BFA42F7-CDEB-4213-BC13-61B2E33B7255"
    },
    {
      "class": "shapeGroup",
      "id": "49BE9807-4399-4DC1-8E78-F1982B56CCC8"
    },
    {
      "class": "shapeGroup",
      "id": "892FFF1F-B0C9-4668-AAFD-3354015F7280"
    },
    {
      "class": "shapeGroup",
      "id": "C8C1FCA2-62FE-405E-87A8-3166D53A26A5"
    },
    {
      "class": "shapeGroup",
      "id": "A8FF84E2-A603-4A05-8FF0-21C2CBC933E7"
    },
    {
      "class": "shapeGroup",
      "id": "553333FF-C86C-4767-B2F0-35301F2AAD09"
    }
  ],
  "name": "Rating",
  "nameIsFixed": true,
  "resizingConstraint": 63,
  "resizingType": 0,
  "rotation": 0,
  "shouldBreakMaskChain": false,
  "style": {
    "_class": "style",
    "endDecorationType": 0,
    "miterLimit": 10,
    "startDecorationType": 0
  },
  "userInfo": {
    "com.animaapp.stc-sketch-plugin": {
      "kModelPropertiesKey": {
      }
    }
  }
}