{
  "_class": "shapePath",
  "booleanOperation": -1,
  "do_objectID": "C43F9ECA-BC57-4DE9-8B03-147D9BE8A140",
  "edited": true,
  "exportOptions": {
    "_class": "exportOptions",
    "do_objectID": "61120972-7169-49CC-A024-4106CCCD309E",
    "exportFormats": [
    ],
    "includedLayerIds": [
    ],
    "layerOptions": 0,
    "shouldTrim": false
  },
  "frame": {
    "_class": "rect",
    "constrainProportions": false,
    "do_objectID": "ED850368-93FB-4C42-8AC4-3F4B01BC19B4",
    "height": 0.5714285714285721,
    "width": 8,
    "x": 0,
    "y": 0
  },
  "isClosed": false,
  "isFlippedHorizontal": false,
  "isFlippedVertical": false,
  "isLocked": false,
  "isVisible": true,
  "layerListExpandedType": 0,
  "name": "Path",
  "nameIsFixed": false,
  "pointRadiusBehaviour": 1,
  "points": [
    {
      "_class": "curvePoint",
      "cornerRadius": 0,
      "curveFrom": "{0, 0}",
      "curveMode": 1,
      "curveTo": "{0, 0}",
      "hasCurveFrom": false,
      "hasCurveTo": false,
      "point": "{0, 0}"
    },
    {
      "_class": "curvePoint",
      "cornerRadius": 0,
      "curveFrom": "{1, 0}",
      "curveMode": 1,
      "curveTo": "{1, 0}",
      "hasCurveFrom": false,
      "hasCurveTo": false,
      "point": "{1, 0}"
    }
  ],
  "resizingConstraint": 63,
  "resizingType": 0,
  "rotation": 0,
  "shouldBreakMaskChain": false
}